[
  {
    "id": 13516,
    "name": "白松乡"
  },
  {
    "id": 13512,
    "name": "八日乡"
  },
  {
    "id": 13511,
    "name": "奔都乡"
  },
  {
    "id": 13517,
    "name": "茨巫乡"
  },
  {
    "id": 13515,
    "name": "贡波乡"
  },
  {
    "id": 13513,
    "name": "古学乡"
  },
  {
    "id": 13507,
    "name": "曲雅贡乡"
  },
  {
    "id": 13510,
    "name": "日龙乡"
  },
  {
    "id": 13508,
    "name": "斯闸乡"
  },
  {
    "id": 13506,
    "name": "松麦镇"
  },
  {
    "id": 40827,
    "name": "县城内"
  },
  {
    "id": 13509,
    "name": "徐龙乡"
  },
  {
    "id": 13514,
    "name": "子庚乡"
  }
]