[
  {
    "id": 21390,
    "name": "蝉战河乡"
  },
  {
    "id": 21395,
    "name": "翠玉傈僳族普米族乡"
  },
  {
    "id": 21386,
    "name": "大兴镇"
  },
  {
    "id": 21396,
    "name": "红桥乡"
  },
  {
    "id": 21398,
    "name": "金棉乡"
  },
  {
    "id": 21392,
    "name": "烂泥箐乡"
  },
  {
    "id": 21393,
    "name": "拉伯乡"
  },
  {
    "id": 21397,
    "name": "宁利乡"
  },
  {
    "id": 21389,
    "name": "跑马坪乡"
  },
  {
    "id": 42156,
    "name": "县城内"
  },
  {
    "id": 21387,
    "name": "西布河乡"
  },
  {
    "id": 21399,
    "name": "西川乡"
  },
  {
    "id": 21391,
    "name": "新营盘乡"
  },
  {
    "id": 21388,
    "name": "永宁坪乡"
  },
  {
    "id": 21394,
    "name": "永宁乡"
  },
  {
    "id": 21400,
    "name": "战河乡"
  }
]