[
  {
    "id": 51330,
    "name": "城区"
  },
  {
    "id": 54431,
    "name": "段店北路街道"
  },
  {
    "id": 40546,
    "name": "段店镇"
  },
  {
    "id": 54432,
    "name": "道德街街道"
  },
  {
    "id": 54430,
    "name": "匡山街道"
  },
  {
    "id": 54429,
    "name": "美里湖街道"
  },
  {
    "id": 54428,
    "name": "南辛庄街道"
  },
  {
    "id": 54427,
    "name": "青年公园街道"
  },
  {
    "id": 40547,
    "name": "吴家堡街道"
  },
  {
    "id": 54426,
    "name": "五里沟街道"
  },
  {
    "id": 54425,
    "name": "西市场街道"
  },
  {
    "id": 54424,
    "name": "营市街街道"
  },
  {
    "id": 54422,
    "name": "振兴街街道"
  },
  {
    "id": 54423,
    "name": "张庄路街道"
  },
  {
    "id": 54421,
    "name": "中大槐树街道"
  }
]