[
  {
    "id": 51696,
    "name": "城区"
  },
  {
    "id": 21081,
    "name": "石板镇"
  },
  {
    "id": 21083,
    "name": "党武镇"
  },
  {
    "id": 58316,
    "name": "贵筑街道"
  },
  {
    "id": 21088,
    "name": "高坡苗族乡"
  },
  {
    "id": 58327,
    "name": "黄河路街道"
  },
  {
    "id": 58325,
    "name": "航空社区"
  },
  {
    "id": 21085,
    "name": "湖潮苗族布依族乡"
  },
  {
    "id": 21086,
    "name": "久安乡"
  },
  {
    "id": 58326,
    "name": "金欣社区"
  },
  {
    "id": 58315,
    "name": "阳光街道"
  },
  {
    "id": 58331,
    "name": "花孟社区"
  },
  {
    "id": 58324,
    "name": "航天社区"
  },
  {
    "id": 58330,
    "name": "金筑街道"
  },
  {
    "id": 21087,
    "name": "麦坪镇"
  },
  {
    "id": 21084,
    "name": "孟关苗族布依族乡"
  },
  {
    "id": 58318,
    "name": "明珠社区"
  },
  {
    "id": 21090,
    "name": "马铃布依族苗族乡"
  },
  {
    "id": 58323,
    "name": "平桥街道"
  },
  {
    "id": 58322,
    "name": "黔江社区"
  },
  {
    "id": 21089,
    "name": "黔陶布依族苗族乡"
  },
  {
    "id": 58321,
    "name": "清浦社区"
  },
  {
    "id": 21076,
    "name": "清溪街道"
  },
  {
    "id": 21080,
    "name": "青岩镇"
  },
  {
    "id": 58320,
    "name": "瑞华社区"
  },
  {
    "id": 58328,
    "name": "三江社区"
  },
  {
    "id": 58329,
    "name": "小孟街道"
  },
  {
    "id": 58317,
    "name": "溪北街道"
  },
  {
    "id": 58319,
    "name": "兴隆社区"
  },
  {
    "id": 21092,
    "name": "羊艾农场"
  },
  {
    "id": 21091,
    "name": "燕楼镇"
  }
]