[
  {
    "id": 52527,
    "name": "城区"
  },
  {
    "id": 16855,
    "name": "陈袁滩镇"
  },
  {
    "id": 16857,
    "name": "大坝镇"
  },
  {
    "id": 16859,
    "name": "瞿靖镇"
  },
  {
    "id": 16862,
    "name": "连湖农场"
  },
  {
    "id": 16854,
    "name": "青铜峡镇"
  },
  {
    "id": 16861,
    "name": "邵岗镇"
  },
  {
    "id": 16863,
    "name": "树新林场"
  },
  {
    "id": 16860,
    "name": "峡口镇"
  },
  {
    "id": 16858,
    "name": "叶盛镇"
  },
  {
    "id": 60493,
    "name": "裕民街道"
  },
  {
    "id": 16856,
    "name": "小坝镇"
  }
]