[
  {
    "id": 45057,
    "name": "陈东乡"
  },
  {
    "id": 45045,
    "name": "城郊镇"
  },
  {
    "id": 45034,
    "name": "城区"
  },
  {
    "id": 45056,
    "name": "大溪乡"
  },
  {
    "id": 45035,
    "name": "凤城街道"
  },
  {
    "id": 45044,
    "name": "峰市镇"
  },
  {
    "id": 45040,
    "name": "抚市镇"
  },
  {
    "id": 45039,
    "name": "高陂镇"
  },
  {
    "id": 45058,
    "name": "高头乡"
  },
  {
    "id": 45054,
    "name": "合溪乡"
  },
  {
    "id": 45052,
    "name": "古竹乡"
  },
  {
    "id": 45049,
    "name": "洪山乡"
  },
  {
    "id": 45041,
    "name": "湖坑镇"
  },
  {
    "id": 45038,
    "name": "湖雷镇"
  },
  {
    "id": 45050,
    "name": "湖山乡"
  },
  {
    "id": 45055,
    "name": "虎岗镇"
  },
  {
    "id": 45047,
    "name": "金砂乡"
  },
  {
    "id": 45036,
    "name": "坎市镇"
  },
  {
    "id": 45043,
    "name": "龙潭镇"
  },
  {
    "id": 45042,
    "name": "培丰镇"
  },
  {
    "id": 45051,
    "name": "岐岭乡"
  },
  {
    "id": 45053,
    "name": "堂堡乡"
  },
  {
    "id": 45037,
    "name": "下洋镇"
  },
  {
    "id": 45048,
    "name": "仙师镇"
  },
  {
    "id": 45046,
    "name": "西溪乡"
  }
]