[
  {
    "id": 13115,
    "name": "白浪镇"
  },
  {
    "id": 13111,
    "name": "城关街道"
  },
  {
    "id": 13113,
    "name": "富水镇"
  },
  {
    "id": 13107,
    "name": "过风楼镇"
  },
  {
    "id": 13109,
    "name": "金丝峡镇"
  },
  {
    "id": 13117,
    "name": "青山镇"
  },
  {
    "id": 13106,
    "name": "清油河镇"
  },
  {
    "id": 13118,
    "name": "水沟镇"
  },
  {
    "id": 13116,
    "name": "试马镇"
  },
  {
    "id": 13108,
    "name": "十里坪镇"
  },
  {
    "id": 13110,
    "name": "魏家台镇"
  },
  {
    "id": 39488,
    "name": "县城内"
  },
  {
    "id": 13114,
    "name": "湘河镇"
  },
  {
    "id": 13112,
    "name": "赵川镇"
  }
]