[
  {
    "id": 33301,
    "name": "长发镇"
  },
  {
    "id": 33303,
    "name": "长青乡"
  },
  {
    "id": 33298,
    "name": "大来镇"
  },
  {
    "id": 52376,
    "name": "郊区内"
  },
  {
    "id": 33308,
    "name": "郊区农垦"
  },
  {
    "id": 33309,
    "name": "莲江口监狱"
  },
  {
    "id": 33297,
    "name": "莲江口镇"
  },
  {
    "id": 33305,
    "name": "平安乡"
  },
  {
    "id": 33307,
    "name": "群胜乡"
  },
  {
    "id": 62049,
    "name": "佳西街道"
  },
  {
    "id": 33306,
    "name": "四丰乡"
  },
  {
    "id": 62050,
    "name": "友谊街道"
  },
  {
    "id": 33300,
    "name": "望江镇"
  },
  {
    "id": 33302,
    "name": "西格木镇"
  },
  {
    "id": 33304,
    "name": "沿江镇"
  },
  {
    "id": 33299,
    "name": "敖其镇"
  }
]