[
  {
    "id": 51668,
    "name": "城区"
  },
  {
    "id": 49493,
    "name": "石羊镇"
  },
  {
    "id": 53557,
    "name": "灌口街道"
  },
  {
    "id": 49490,
    "name": "聚源镇"
  },
  {
    "id": 71625,
    "name": "奎光塔街道"
  },
  {
    "id": 71626,
    "name": "银杏街道"
  },
  {
    "id": 49496,
    "name": "龙池镇"
  },
  {
    "id": 49489,
    "name": "蒲阳镇"
  },
  {
    "id": 49502,
    "name": "青城山镇"
  },
  {
    "id": 49492,
    "name": "天马镇"
  },
  {
    "id": 53558,
    "name": "幸福街道"
  },
  {
    "id": 49488,
    "name": "玉堂镇"
  }
]