[
  {
    "id": 16628,
    "name": "城台乡"
  },
  {
    "id": 16629,
    "name": "达拉乡"
  },
  {
    "id": 16627,
    "name": "峰堆乡"
  },
  {
    "id": 16616,
    "name": "高店镇"
  },
  {
    "id": 16615,
    "name": "高庙镇"
  },
  {
    "id": 16619,
    "name": "共和乡"
  },
  {
    "id": 16611,
    "name": "洪水镇"
  },
  {
    "id": 16617,
    "name": "瞿昙镇"
  },
  {
    "id": 16623,
    "name": "芦化乡"
  },
  {
    "id": 16621,
    "name": "李家乡"
  },
  {
    "id": 16618,
    "name": "马营乡"
  },
  {
    "id": 16624,
    "name": "马厂乡"
  },
  {
    "id": 16612,
    "name": "碾伯镇"
  },
  {
    "id": 16625,
    "name": "蒲台乡"
  },
  {
    "id": 16614,
    "name": "寿乐镇"
  },
  {
    "id": 37712,
    "name": "县城内"
  },
  {
    "id": 16622,
    "name": "下营乡"
  },
  {
    "id": 16613,
    "name": "雨润镇"
  },
  {
    "id": 16626,
    "name": "中坝乡"
  },
  {
    "id": 16620,
    "name": "中岭乡"
  }
]