[
  {
    "id": 49432,
    "name": "德源镇"
  },
  {
    "id": 49426,
    "name": "合作街道"
  },
  {
    "id": 49425,
    "name": "红光街道"
  },
  {
    "id": 49423,
    "name": "郫筒街道"
  },
  {
    "id": 49436,
    "name": "三道堰镇"
  },
  {
    "id": 49427,
    "name": "团结镇"
  },
  {
    "id": 49429,
    "name": "唐昌镇"
  },
  {
    "id": 71584,
    "name": "西园街道"
  },
  {
    "id": 49422,
    "name": "县城内"
  },
  {
    "id": 49424,
    "name": "犀浦镇"
  },
  {
    "id": 49433,
    "name": "友爱镇"
  },
  {
    "id": 49430,
    "name": "安德镇"
  },
  {
    "id": 49431,
    "name": "安靖镇"
  }
]