[
  {
    "id": 16337,
    "name": "白土卜子乡"
  },
  {
    "id": 16336,
    "name": "白音特拉乡"
  },
  {
    "id": 16335,
    "name": "朝阳镇"
  },
  {
    "id": 16333,
    "name": "城关镇"
  },
  {
    "id": 37863,
    "name": "城区"
  },
  {
    "id": 16343,
    "name": "达盖滩乡"
  },
  {
    "id": 16341,
    "name": "德包图乡"
  },
  {
    "id": 16344,
    "name": "德善乡"
  },
  {
    "id": 16338,
    "name": "公腊胡洞乡"
  },
  {
    "id": 60910,
    "name": "长顺镇"
  },
  {
    "id": 16339,
    "name": "六十顷乡"
  },
  {
    "id": 16340,
    "name": "六支箭乡"
  },
  {
    "id": 16334,
    "name": "七号镇"
  },
  {
    "id": 16342,
    "name": "二道河乡"
  }
]