[
  {
    "id": 41718,
    "name": "保税区"
  },
  {
    "id": 51384,
    "name": "城区"
  },
  {
    "id": 59513,
    "name": "翠香街道"
  },
  {
    "id": 59515,
    "name": "大学园区"
  },
  {
    "id": 41714,
    "name": "担杆镇"
  },
  {
    "id": 41712,
    "name": "桂山镇"
  },
  {
    "id": 41720,
    "name": "国家高新区"
  },
  {
    "id": 41717,
    "name": "拱北街道"
  },
  {
    "id": 41711,
    "name": "横琴镇"
  },
  {
    "id": 41722,
    "name": "洪湾商贸物流中心"
  },
  {
    "id": 129141,
    "name": "凤山街道"
  },
  {
    "id": 41716,
    "name": "吉大街道"
  },
  {
    "id": 41723,
    "name": "金鼎工业园"
  },
  {
    "id": 41715,
    "name": "金鼎镇"
  },
  {
    "id": 59511,
    "name": "梅华街道"
  },
  {
    "id": 41713,
    "name": "万山镇"
  },
  {
    "id": 41721,
    "name": "南屏科技园"
  },
  {
    "id": 41710,
    "name": "南屏镇"
  },
  {
    "id": 41708,
    "name": "前山街道"
  },
  {
    "id": 59520,
    "name": "前山商贸物流中心"
  },
  {
    "id": 59514,
    "name": "狮山街道"
  },
  {
    "id": 41719,
    "name": "唐家湾镇"
  },
  {
    "id": 41709,
    "name": "湾仔街道"
  },
  {
    "id": 59512,
    "name": "香湾街道"
  }
]