[
  {
    "id": 7567,
    "name": "柴湖镇"
  },
  {
    "id": 7558,
    "name": "长寿镇"
  },
  {
    "id": 7568,
    "name": "长滩镇"
  },
  {
    "id": 51727,
    "name": "城区"
  },
  {
    "id": 56992,
    "name": "大口林场"
  },
  {
    "id": 55245,
    "name": "石门水库"
  },
  {
    "id": 7565,
    "name": "石牌镇"
  },
  {
    "id": 7569,
    "name": "东桥镇"
  },
  {
    "id": 7559,
    "name": "丰乐镇"
  },
  {
    "id": 129453,
    "name": "康桥湖农场"
  },
  {
    "id": 51214,
    "name": "官庄湖管理区"
  },
  {
    "id": 129454,
    "name": "东岳种畜场"
  },
  {
    "id": 55246,
    "name": "黄坡水库"
  },
  {
    "id": 56993,
    "name": "湖北钟祥胡集经济技术开发区"
  },
  {
    "id": 7560,
    "name": "胡集镇"
  },
  {
    "id": 7566,
    "name": "旧口镇"
  },
  {
    "id": 7572,
    "name": "九里乡"
  },
  {
    "id": 7570,
    "name": "客店镇"
  },
  {
    "id": 55242,
    "name": "罗汉寺街道"
  },
  {
    "id": 55240,
    "name": "罗汉寺种畜场"
  },
  {
    "id": 7562,
    "name": "磷矿镇"
  },
  {
    "id": 7564,
    "name": "冷水镇"
  },
  {
    "id": 55239,
    "name": "南湖原种场"
  },
  {
    "id": 55243,
    "name": "盘石岭林场"
  },
  {
    "id": 54054,
    "name": "七里湖"
  },
  {
    "id": 7561,
    "name": "双河镇"
  },
  {
    "id": 55241,
    "name": "双桥原种场"
  },
  {
    "id": 7563,
    "name": "文集镇"
  },
  {
    "id": 55244,
    "name": "温峡水库"
  },
  {
    "id": 7557,
    "name": "洋梓镇"
  },
  {
    "id": 55238,
    "name": "郢中街道"
  },
  {
    "id": 7571,
    "name": "张集镇"
  },
  {
    "id": 56994,
    "name": "湖北钟祥经济开发区"
  }
]