[
  {
    "id": 33778,
    "name": "成富朝鲜族满族乡"
  },
  {
    "id": 33773,
    "name": "东建乡"
  },
  {
    "id": 33771,
    "name": "凤岗镇"
  },
  {
    "id": 33780,
    "name": "红兴隆分局局直"
  },
  {
    "id": 33775,
    "name": "建设乡"
  },
  {
    "id": 33770,
    "name": "龙山镇"
  },
  {
    "id": 33774,
    "name": "庆丰乡"
  },
  {
    "id": 58176,
    "name": "双鸭山农场"
  },
  {
    "id": 37033,
    "name": "县城内"
  },
  {
    "id": 33772,
    "name": "兴盛乡"
  },
  {
    "id": 33769,
    "name": "兴隆镇"
  },
  {
    "id": 33777,
    "name": "新镇乡"
  },
  {
    "id": 33776,
    "name": "友邻乡"
  },
  {
    "id": 33768,
    "name": "友谊镇"
  }
]