[
  {
    "id": 11468,
    "name": "勃利镇"
  },
  {
    "id": 11477,
    "name": "北兴农场"
  },
  {
    "id": 11467,
    "name": "大四站镇"
  },
  {
    "id": 11476,
    "name": "吉兴乡"
  },
  {
    "id": 11474,
    "name": "抢垦乡"
  },
  {
    "id": 11471,
    "name": "青山乡"
  },
  {
    "id": 11469,
    "name": "双河镇"
  },
  {
    "id": 62063,
    "name": "新起街道"
  },
  {
    "id": 62064,
    "name": "新华街道"
  },
  {
    "id": 62065,
    "name": "元明街道"
  },
  {
    "id": 62066,
    "name": "铁西街道"
  },
  {
    "id": 62067,
    "name": "城西街道"
  },
  {
    "id": 11470,
    "name": "倭肯镇"
  },
  {
    "id": 37079,
    "name": "县城内"
  },
  {
    "id": 11466,
    "name": "小五站镇"
  },
  {
    "id": 11475,
    "name": "杏树乡"
  },
  {
    "id": 11473,
    "name": "永恒乡"
  }
]