[
  {
    "id": 742,
    "name": "大庆市"
  },
  {
    "id": 793,
    "name": "大兴安岭地区"
  },
  {
    "id": 727,
    "name": "鹤岗市"
  },
  {
    "id": 698,
    "name": "哈尔滨市"
  },
  {
    "id": 776,
    "name": "黑河市"
  },
  {
    "id": 765,
    "name": "佳木斯市"
  },
  {
    "id": 712,
    "name": "齐齐哈尔市"
  },
  {
    "id": 737,
    "name": "鸡西市"
  },
  {
    "id": 757,
    "name": "牡丹江市"
  },
  {
    "id": 773,
    "name": "七台河市"
  },
  {
    "id": 731,
    "name": "双鸭山市"
  },
  {
    "id": 782,
    "name": "绥化市"
  },
  {
    "id": 753,
    "name": "伊春市"
  }
]