[
  {
    "id": 4101,
    "name": "昌北区"
  },
  {
    "id": 3507,
    "name": "东湖区"
  },
  {
    "id": 4039,
    "name": "高新区"
  },
  {
    "id": 40847,
    "name": "红谷滩区"
  },
  {
    "id": 1829,
    "name": "进贤县"
  },
  {
    "id": 1828,
    "name": "南昌县"
  },
  {
    "id": 40846,
    "name": "青山湖区"
  },
  {
    "id": 3505,
    "name": "青云谱区"
  },
  {
    "id": 3504,
    "name": "湾里区"
  },
  {
    "id": 3506,
    "name": "西湖区"
  },
  {
    "id": 3502,
    "name": "新建区"
  },
  {
    "id": 1830,
    "name": "安义县"
  }
]